pylibspot.py
pylibspot-1.1.3.dist-info/LICENSE
pylibspot-1.1.3.dist-info/WHEEL
pylibspot-1.1.3.dist-info/METADATA
pylibspot-1.1.3.dist-info/RECORD
