Metadata-Version: 2.1
Name: pylibspot
Version: 1.1.3
Summary: PyPI version of the python3 bindings to libspot
Home-page: https://asiffer.github.io/libspot/
License: GPL-3.0-only
Author: Alban Siffer
Author-email: alban.siffer@irisa.fr
Maintainer: Alban Siffer
Maintainer-email: alban.siffer@irisa.fr
Requires-Python: >=3,<4
Classifier: License :: OSI Approved :: GNU General Public License v3 (GPLv3)
Classifier: Programming Language :: Python :: 3
Classifier: Programming Language :: Python :: 3.10
Classifier: Programming Language :: Python :: 3.4
Classifier: Programming Language :: Python :: 3.5
Classifier: Programming Language :: Python :: 3.6
Classifier: Programming Language :: Python :: 3.7
Classifier: Programming Language :: Python :: 3.8
Classifier: Programming Language :: Python :: 3.9
Project-URL: Repository, https://github.com/asiffer/python3-libspot
